[
  {
    "P_KIND": "0301",
    "P_VOICE_T": "망내기본제공",
    "P_DATA": "750MB",
    "P_VAT": null,
    "P_AMT": 30800,
    "P_LINK": null,
    "P_VOICE": "130분",
    "P_DC24M": 21450,
    "P_DC12M": 21560,
    "P_NO": 25,
    "P_NAME": "우리끼리 U 308",
    "P_SMS": "기본제공",
    "P_SMS_T": null,
    "P_DC6M": 30800,
    "P_DATA_T": "이월",
    "IS_USE": "O"
  },
  {
    "P_KIND": "0301",
    "P_VOICE_T": "망내기본제공",
    "P_DATA": "750MB",
    "P_VAT": null,
    "P_AMT": 30800,
    "P_LINK": null,
    "P_VOICE": "130분",
    "P_DC24M": 21450,
    "P_DC12M": 21560,
    "P_NO": 24,
    "P_NAME": "우리끼리 U 308 안심",
    "P_SMS": "기본제공",
    "P_SMS_T": null,
    "P_DC6M": 30800,
    "P_DATA_T": "안심차단",
    "IS_USE": "O"
  },
  {
    "P_KIND": "0301",
    "P_VOICE_T": "망내기본제공",
    "P_DATA": "1.5GB",
    "P_VAT": null,
    "P_AMT": 37400,
    "P_LINK": null,
    "P_VOICE": "185분",
    "P_DC24M": 28050,
    "P_DC12M": 26180,
    "P_NO": 3,
    "P_NAME": "우리끼리  U 374",
    "P_SMS": "기본제공",
    "P_SMS_T": null,
    "P_DC6M": 37400,
    "P_DATA_T": "이월",
    "IS_USE": "O"
  },
  {
    "P_KIND": "0301",
    "P_VOICE_T": "망내기본제공",
    "P_DATA": "1.5GB",
    "P_VAT": null,
    "P_AMT": 37400,
    "P_LINK": null,
    "P_VOICE": "185분",
    "P_DC24M": 28050,
    "P_DC12M": 26180,
    "P_NO": 21,
    "P_NAME": "우리끼리 U 374 안심",
    "P_SMS": "기본제공",
    "P_SMS_T": null,
    "P_DC6M": 37400,
    "P_DATA_T": "안심차단",
    "IS_USE": "O"
  },
  {
    "P_KIND": "0301",
    "P_VOICE_T": "망내기본제공",
    "P_DATA": "2.5GB",
    "P_VAT": null,
    "P_AMT": 45100,
    "P_LINK": null,
    "P_VOICE": "250분",
    "P_DC24M": 33770,
    "P_DC12M": 31570,
    "P_NO": 13,
    "P_NAME": "우리끼리 U 451",
    "P_SMS": "기본제공",
    "P_SMS_T": null,
    "P_DC6M": 45100,
    "P_DATA_T": "이월",
    "IS_USE": "O"
  },
  {
    "P_KIND": "0301",
    "P_VOICE_T": "망내기본제공",
    "P_DATA": "2.5GB",
    "P_VAT": null,
    "P_AMT": 45100,
    "P_LINK": null,
    "P_VOICE": "250분",
    "P_DC24M": 33770,
    "P_DC12M": 31570,
    "P_NO": 22,
    "P_NAME": "우리끼리 U 451 안심",
    "P_SMS": "기본제공",
    "P_SMS_T": null,
    "P_DC6M": 45100,
    "P_DATA_T": "안심차단",
    "IS_USE": "O"
  },
  {
    "P_KIND": "0302",
    "P_VOICE_T": "부가30분",
    "P_DATA": "300MB",
    "P_VAT": null,
    "P_AMT": 32890,
    "P_LINK": null,
    "P_VOICE": "기본제공",
    "P_DC24M": 29590,
    "P_DC12M": 22990,
    "P_NO": 26,
    "P_NAME": "누구나 U 329",
    "P_SMS": "기본제공",
    "P_SMS_T": null,
    "P_DC6M": 32890,
    "P_DATA_T": "밀당",
    "IS_USE": "O"
  },
  {
    "P_KIND": "0302",
    "P_VOICE_T": "부가30분",
    "P_DATA": "1GB",
    "P_VAT": null,
    "P_AMT": 38390,
    "P_LINK": null,
    "P_VOICE": "기본제공",
    "P_DC24M": 38390,
    "P_DC12M": 26800,
    "P_NO": 30,
    "P_NAME": "누구나 U 383",
    "P_SMS": "기본제공",
    "P_SMS_T": null,
    "P_DC6M": 38390,
    "P_DATA_T": "밀당",
    "IS_USE": "O"
  },
  {
    "P_KIND": "0302",
    "P_VOICE_T": "부가200분",
    "P_DATA": "5GB",
    "P_VAT": null,
    "P_AMT": 56100,
    "P_LINK": null,
    "P_VOICE": "기본제공",
    "P_DC24M": 50600,
    "P_DC12M": 39270,
    "P_NO": 4,
    "P_NAME": "누구나 U 561",
    "P_SMS": "기본제공",
    "P_SMS_T": null,
    "P_DC6M": 56100,
    "P_DATA_T": "안심차단",
    "IS_USE": "O"
  },
  {
    "P_KIND": "0302",
    "P_VOICE_T": "부가200분",
    "P_DATA": "10GB",
    "P_VAT": null,
    "P_AMT": 65890,
    "P_LINK": null,
    "P_VOICE": "기본제공",
    "P_DC24M": 59290,
    "P_DC12M": 46090,
    "P_NO": 5,
    "P_NAME": "누구나 U 659",
    "P_SMS": "기본제공",
    "P_SMS_T": null,
    "P_DC6M": 65890,
    "P_DATA_T": "+일2GB",
    "IS_USE": "O"
  },
  {
    "P_KIND": "0303",
    "P_VOICE_T": null,
    "P_DATA": "400MB",
    "P_VAT": null,
    "P_AMT": 9900,
    "P_LINK": null,
    "P_VOICE": "50분",
    "P_DC24M": 9900,
    "P_DC12M": 9900,
    "P_NO": 18,
    "P_NAME": "실속 알뜰",
    "P_SMS": "100건",
    "P_SMS_T": null,
    "P_DC6M": 9900,
    "P_DATA_T": "안심차단",
    "IS_USE": "O"
  },
  {
    "P_KIND": "0303",
    "P_VOICE_T": null,
    "P_DATA": "750MB",
    "P_VAT": null,
    "P_AMT": 29700,
    "P_LINK": null,
    "P_VOICE": "160분",
    "P_DC24M": 29700,
    "P_DC12M": 20790,
    "P_NO": 33,
    "P_NAME": "실속 U 297",
    "P_SMS": "200건",
    "P_SMS_T": null,
    "P_DC6M": 29700,
    "P_DATA_T": null,
    "IS_USE": "O"
  },
  {
    "P_KIND": "0303",
    "P_VOICE_T": null,
    "P_DATA": "2.5GB",
    "P_VAT": null,
    "P_AMT": 41800,
    "P_LINK": null,
    "P_VOICE": "250분",
    "P_DC24M": 41800,
    "P_DC12M": 29260,
    "P_NO": 32,
    "P_NAME": "실속 U 418",
    "P_SMS": "250건",
    "P_SMS_T": null,
    "P_DC6M": 41800,
    "P_DATA_T": null,
    "IS_USE": "O"
  },
  {
    "P_KIND": "0303",
    "P_VOICE_T": null,
    "P_DATA": "6GB",
    "P_VAT": null,
    "P_AMT": 50600,
    "P_LINK": null,
    "P_VOICE": "350분",
    "P_DC24M": 39600,
    "P_DC12M": 35420,
    "P_NO": 17,
    "P_NAME": "실속 U 506 안심",
    "P_SMS": "350건",
    "P_SMS_T": null,
    "P_DC6M": 50600,
    "P_DATA_T": "안심차단",
    "IS_USE": "O"
  },
  {
    "P_KIND": "0303",
    "P_VOICE_T": null,
    "P_DATA": "10GB",
    "P_VAT": null,
    "P_AMT": 59400,
    "P_LINK": null,
    "P_VOICE": "450분",
    "P_DC24M": 59400,
    "P_DC12M": 41580,
    "P_NO": 31,
    "P_NAME": "실속 U 594",
    "P_SMS": "450분",
    "P_SMS_T": null,
    "P_DC6M": 59400,
    "P_DATA_T": null,
    "IS_USE": "O"
  },
  {
    "P_KIND": "0303",
    "P_VOICE_T": null,
    "P_DATA": "10GB",
    "P_VAT": null,
    "P_AMT": 59400,
    "P_LINK": null,
    "P_VOICE": "450분",
    "P_DC24M": 47300,
    "P_DC12M": 41580,
    "P_NO": 27,
    "P_NAME": "실속 U 594 안심",
    "P_SMS": "450건",
    "P_SMS_T": null,
    "P_DC6M": 59400,
    "P_DATA_T": "안심차단",
    "IS_USE": "O"
  },
  {
    "P_KIND": "0304",
    "P_VOICE_T": null,
    "P_DATA": "10.0GB",
    "P_VAT": null,
    "P_AMT": 49500,
    "P_LINK": null,
    "P_VOICE": "-",
    "P_DC24M": 38500,
    "P_DC12M": 36000,
    "P_NO": 19,
    "P_NAME": "패드 10.0 안심",
    "P_SMS": "-",
    "P_SMS_T": null,
    "P_DC6M": 49500,
    "P_DATA_T": "안심차단",
    "IS_USE": "O"
  },
  {
    "P_KIND": "0305",
    "P_VOICE_T": "조절",
    "P_DATA": null,
    "P_VAT": null,
    "P_AMT": 19800,
    "P_LINK": null,
    "P_VOICE": "27,000그루",
    "P_DC24M": 19800,
    "P_DC12M": 13860,
    "P_NO": 34,
    "P_NAME": "그린 U 198",
    "P_SMS": null,
    "P_SMS_T": null,
    "P_DC6M": 19800,
    "P_DATA_T": null,
    "IS_USE": "O"
  },
  {
    "P_KIND": "0305",
    "P_VOICE_T": "조절",
    "P_DATA": null,
    "P_VAT": null,
    "P_AMT": 29700,
    "P_LINK": null,
    "P_VOICE": "54,000그루",
    "P_DC24M": 29700,
    "P_DC12M": 20790,
    "P_NO": 35,
    "P_NAME": "그린 U 297",
    "P_SMS": null,
    "P_SMS_T": null,
    "P_DC6M": 29700,
    "P_DATA_T": null,
    "IS_USE": "O"
  },
  {
    "P_KIND": "0307",
    "P_VOICE_T": null,
    "P_DATA": "6.0GB",
    "P_VAT": null,
    "P_AMT": 31900,
    "P_LINK": null,
    "P_VOICE": "-",
    "P_DC24M": 31900,
    "P_DC12M": 28710,
    "P_NO": 29,
    "P_NAME": "Biz 패드 6.0 안심",
    "P_SMS": "-",
    "P_SMS_T": null,
    "P_DC6M": 31900,
    "P_DATA_T": "안심차단",
    "IS_USE": "O"
  },
  {
    "P_KIND": "0307",
    "P_VOICE_T": "부가30분",
    "P_DATA": "3GB",
    "P_VAT": null,
    "P_AMT": 49300,
    "P_LINK": null,
    "P_VOICE": "기본제공",
    "P_DC24M": 44900,
    "P_DC12M": 44350,
    "P_NO": 16,
    "P_NAME": "Biz 누구나 U 493",
    "P_SMS": "기본제공",
    "P_SMS_T": null,
    "P_DC6M": 49300,
    "P_DATA_T": "밀당",
    "IS_USE": "O"
  },
  {
    "P_KIND": "0307",
    "P_VOICE_T": "부가200분",
    "P_DATA": "10GB",
    "P_VAT": null,
    "P_AMT": 65890,
    "P_LINK": null,
    "P_VOICE": "기본제공",
    "P_DC24M": 65890,
    "P_DC12M": 59290,
    "P_NO": 28,
    "P_NAME": "Biz 누구나 U 659",
    "P_SMS": "기본제공",
    "P_SMS_T": null,
    "P_DC6M": 65890,
    "P_DATA_T": "+일2GB",
    "IS_USE": "O"
  },
  {
    "P_KIND": "0307",
    "P_VOICE_T": "부가200분",
    "P_DATA": "25GB",
    "P_VAT": null,
    "P_AMT": 108900,
    "P_LINK": null,
    "P_VOICE": "기본제공",
    "P_DC24M": 93500,
    "P_DC12M": 98010,
    "P_NO": 6,
    "P_NAME": "Biz 누구나 U 1089",
    "P_SMS": "기본제공",
    "P_SMS_T": null,
    "P_DC6M": 108900,
    "P_DATA_T": "+일2GB",
    "IS_USE": "O"
  }
]
